README.md
setup.py
icons/proto.png
icons/proto_red.png
protonvpn_gtk/__init__.py
protonvpn_gtk/__version__.py
protonvpn_gtk/run.py
protonvpn_gtk.egg-info/PKG-INFO
protonvpn_gtk.egg-info/SOURCES.txt
protonvpn_gtk.egg-info/dependency_links.txt
protonvpn_gtk.egg-info/entry_points.txt
protonvpn_gtk.egg-info/requires.txt
protonvpn_gtk.egg-info/top_level.txt
protonvpn_gtk/ui/__init__.py
protonvpn_gtk/ui/app.py
protonvpn_gtk/ui/indicator.py
protonvpn_gtk/ui/status.py
protonvpn_gtk/utils/__init__.py
protonvpn_gtk/utils/core.py
protonvpn_gtk/utils/system.py